mongodb_connect_automation/__init__.py
mongodb_connect_automation/mongo_crud.py
mongodb_connect_automation-0.0.2.dist-info/METADATA
mongodb_connect_automation-0.0.2.dist-info/WHEEL
mongodb_connect_automation-0.0.2.dist-info/top_level.txt
mongodb_connect_automation-0.0.2.dist-info/RECORD
